llm_task_agents/__init__.py
llm_task_agents/agent_factory.py
llm_task_agents/agents/__init__.py
llm_task_agents/agents/agent.py
llm_task_agents/agents/graph_agent.py
llm_task_agents/agents/image_classification_agent.py
llm_task_agents/agents/json_agent.py
llm_task_agents/agents/sql_agent.py
llm_task_agents/agents/subtasks_agent.py
llm_task_agents/agents/text_classification_agent.py
tests/__init__.py
tests/test_graph_agent.py
tests/test_image_agent.py
tests/test_json_agent.py
tests/test_sql_agent.py
tests/test_subtasks_agent.py
tests/test_text_agent.py
llm_task_agents-0.1.5.dist-info/METADATA
llm_task_agents-0.1.5.dist-info/WHEEL
llm_task_agents-0.1.5.dist-info/top_level.txt
llm_task_agents-0.1.5.dist-info/RECORD
