Metadata-Version: 2.1
Name: llm-task-agents
Version: 0.1.5
Summary: A collection of preset efficient prompts packaged into LLM agents.
Home-page: https://github.com/alfredwallace7/llm-task-agents
Author: Alfred Wallace
Author-email: alfred.wallace@netcraft.fr
Classifier: Programming Language :: Python :: 3
Classifier: License :: OSI Approved :: MIT License
Classifier: Operating System :: OS Independent
Requires-Python: >=3.6
Requires-Dist: ollama
Requires-Dist: sqlalchemy
Requires-Dist: mysqlclient
